Metadata-Version: 2.3
Name: fastapi-code-generator
Version: 0.5.4
Summary: 
License: MIT
Author: Koudai Aono
Author-email: koxudaxi@gmail.com
Requires-Python: >=3.9,<3.13
Classifier: Development Status :: 2 - Pre-Alpha
Classifier: License :: OSI Approved :: MIT License
Classifier: Natural Language :: English
Classifier: Programming Language :: Python :: 3
Classifier: Programming Language :: Python :: 3.9
Classifier: Programming Language :: Python :: 3.10
Classifier: Programming Language :: Python :: 3.11
Classifier: Programming Language :: Python :: 3.12
Classifier: Programming Language :: Python :: Implementation :: CPython
Requires-Dist: PySnooper (>=0.4.1,<1.2.0)
Requires-Dist: datamodel-code-generator[http] (==0.30.1)
Requires-Dist: jinja2 (>=2.11.2,<4.0.0)
Requires-Dist: pydantic (>=2.8,<3.0)
Requires-Dist: stringcase (>=1.2.0,<2.0.0)
Requires-Dist: typer[all] (>=0.2.1,<0.13.0)
Project-URL: Homepage, https://github.com/koxudaxi/fastapi-code-generator
Project-URL: Repository, https://github.com/koxudaxi/fastapi-code-generator
